pygtfslib/__init__.py
pygtfslib/fast_csv.py
pygtfslib/mot.py
pygtfslib/spatial.py
pygtfslib/temporal.py
pygtfslib/test/__init__.py
pygtfslib/test/test_spatial.py
pygtfslib/test/test_temporal.py
pygtfslib-0.1.3.dist-info/LICENSE
pygtfslib-0.1.3.dist-info/METADATA
pygtfslib-0.1.3.dist-info/WHEEL
pygtfslib-0.1.3.dist-info/top_level.txt
pygtfslib-0.1.3.dist-info/RECORD
