Metadata-Version: 2.1
Name: pygtfslib
Version: 0.1.3
Summary: A Python Library for GTFS
Author-email: Alexander Held | geOps <alexander.held@geops.com>
Maintainer-email: Alexander Held | geOps <alexander.held@geops.com>
License: MIT License
Project-URL: homepage, https://github.com/geops/pygtfslib
Project-URL: geOps, https://geops.com/en
Keywords: public transport,GTFS,library,efficient
Classifier: Development Status :: 3 - Alpha
Classifier: Programming Language :: Python :: 3
Classifier: Intended Audience :: Developers
Classifier: License :: OSI Approved :: MIT License
Classifier: Topic :: Software Development :: Libraries :: Python Modules
Classifier: Topic :: Utilities
Requires-Python: >=3.7
License-File: LICENSE
Requires-Dist: python-dateutil
